Metadata-Version: 1.1
Name: idegovuz
Version: 0.2
Summary: id.egov.uz provider for django-allauth
Home-page: https://github.com/vodiylik/allauth-idegovuz
Author: Shukrullo Turgunov
Author-email: sh@turgunov.uz
License: MIT
Keywords: id.egov.uz,id,allauth,provider
Platform: UNKNOWN
Classifier: Programming Language :: Python :: 3
Classifier: License :: OSI Approved :: MIT License
Classifier: Operating System :: OS Independent
